[
  {
    "object name" : "Alpha Centauri A",
    "visual magnitude" : "-0.27",
    "visual luminosity" : "1.519*sun",
    "object type": "star",
    "mass" : "1.1*sun",
    "distance": "4.37 lightyears, 1.34pc",
    "synonyms": {
      "object name": [
        "Rigil Kentaurus"
      ]
    }
  },
  {
    "object name" : "Alpha Centauri B",
    "visual luminosity" : "0.445*sun",
    "mass" : ".907*sun",
    "visual magnitude" : "n/a",
    "distance": "4.37 lightyears, 1.34pc"
  },
  {
    "object name" : "Alpha Centauri C",
    "visual luminosity" : "-0.27",
    "mass" : "n/a",
    "visual magnitude" : "n/a",
    "orbits" : "n/a",
    "object type" : "star, red dwarf",
    "distance" : "4.24 lightyears, 1.30pc",
    "synonyms": {
      "object name": [
        "Proxima Centauri"
      ]
    }
  },
  {
    "object name" : "Proxima Centauri b",
    "visual luminosity" : "n/a",
    "mass" : "0.134*sun, 1.27*earth",
    "radius" : "0.141*sun, 1.1+/-0.3*earth",
    "visual magnitude" : "n/a",
    "object type" : "planet",
    "orbits" : "Alpha Centauri C",
    "distance" : "4.2 lightyears, 1.30pc",
    "_url": "https://en.wikipedia.org/wiki/Proxima_Centauri_b",
    "synonyms": {
      "object name": [
        "Proxima b"
      ]
    }
  },
  {
    "object name" : "Mars",
    "visual luminosity" : "n/a",
    "orbit radius" : "1.66AU-1.523679AU",
    "eccentricity" : "0.0934",
    "orbital period" : "1.880years, 668 sols",
    "mass" : "0.107*earth",
    "radius" : "0.53*earth, 3.390 km",
    "visual magnitude" : "+1.6 to -3.0",
    "object type" : "planet",
    "orbits" : "Sun",
    "distance" : "n/a",
    "_url" : "https://en.wikipedia.org/wiki/Mars"
  },
  {
    "object name" : "earth",
    "visual luminosity" : "n/a",
    "orbit radius" : "1.016 - 0.983 AU, 152,100,000km - 14,.095,000km",
    "eccentricity" : "0.0167",
    "orbital period" : "1years, 365.256363004 d 668 sols",
    "mass" : "1*earth, 5.2*10^24kg",
    "radius" : "1*earth, 6371km",
    "visual magnitude" : "n/a",
    "albedo" : "0.367",
    "object type" : "planet",
    "orbits" : "Sun",
    "distance" : "0",
    "_url" : "https://en.wikipedia.org/wiki/Earth",
    "synonyms" : {
      "object name": [
        "blue planet"
      ]
    }
  },
  {
    "object name" : "Sun",
    "visual luminosity" : "n/a",
    "orbit radius" : "1.016 - 0.983 AU, 152,100,000km - 14,.095,000km",
    "mass" : "333,000*earth, 1.989×10^30 kg",
    "radius" : "109*earth, 695700km",
    "visual magnitude" : "-27",
    "object type" : "star",
    "distance" : "1au; 1.496x10^8 km, 8min 19s at light speed",
    "_url" : "https://en.wikipedia.org/wiki/Sun"
  }
]
